README.md
setup.cfg
setup.py
hyperchamber/__init__.py
hyperchamber/config.py
hyperchamber/selector.py
hyperchamber.egg-info/PKG-INFO
hyperchamber.egg-info/SOURCES.txt
hyperchamber.egg-info/dependency_links.txt
hyperchamber.egg-info/requires.txt
hyperchamber.egg-info/top_level.txt
hyperchamber/io/__init__.py