Metadata-Version: 1.0
Name: hyperchamber
Version: 0.3.1
Summary: Tune and optimize your hyperparameters
Home-page: https://github.com/255bits/hyperchamber
Author: 255bits
Author-email: support@255bits.com
License: MIT
Platform: UNKNOWN
